{
  "class": "aves",
  "order": "coraciiformes",
  "name": "coraciiformes",
  "name-jp": "ブッポウソウ目",
  "name-cn": "佛法僧目",
  "type": "order",
  "children": [
    {
      "name": "meropidae",
      "name-jp": "ハチクイ科",
      "name-cn": "蜂虎科",
      "type": "family",
      "children": [
        {
          "name": "merops",
          "name-jp": "ハチクイ属",
          "name-cn": "蜂虎属",
          "type": "genus",
          "icon-children": [
            {
              "name": "merops nubicus",
              "name-jp": "キタベニハチクイ",
              "name-cn": "北方洋红蜂虎",
              "type": "species",
              "icon": "/icon/キタベニハチクイ.jpg",
              "hasWild": false
            }
          ]
        }
      ]
    },
    {
      "name": "coraciidae",
      "name-jp": "ブッポウソウ科",
      "name-cn": "佛法僧科",
      "type": "family",
      "children": [
        {
          "name": "coracias",
          "name-jp": "ニシブッポウソウ属",
          "name-cn": "佛法僧属",
          "type": "genus",
          "icon-children": [
            {
              "name": "coracias caudatus",
              "name-jp": "ライラックニシブッポウソウ",
              "name-cn": "紫胸佛法僧",
              "type": "species",
              "icon": "/icon/ライラックニシブッポウソウ.jpg",
              "hasWild": false
            }
          ]
        }
      ]
    },
    {
      "name": "alcedinidae",
      "name-jp": "カワセミ科",
      "name-cn": "翠鸟科",
      "type": "family",
      "children": [
        {
          "name": "alcedininae",
          "name-jp": "カワセミ亜科",
          "name-cn": "翠鸟亚科",
          "type": "subfamily",
          "children": [
            {
              "name": "alcedo",
              "name-jp": "カワセミ属",
              "name-cn": "翠鸟属",
              "type": "genus",
              "icon-children": [
                {
                  "name": "alcedo atthis",
                  "name-jp": "カワセミ",
                  "name-cn": "普通翠鸟",
                  "type": "species",
                  "icon": "/icon/カワセミ.jpg",
                  "hasWild": true
                }
              ]
            }
          ]
        },
        {
          "name": "halcyoninae",
          "name-jp": "ショウビン亜科",
          "name-cn": "翡翠亚科",
          "type": "subfamily",
          "children": [
            {
              "name": "halcyon",
              "name-jp": "ヤマショウビン属",
              "name-cn": "翡翠属",
              "type": "genus",
              "icon-children": [
                {
                  "name": "halcyon coromanda",
                  "name-jp": "アカショウビン",
                  "name-cn": "赤翡翠",
                  "type": "species",
                  "icon": "/icon/アカショウビン.jpg",
                  "hasWild": false
                }
              ]
            },
            {
              "name": "dacelo",
              "name-jp": "ワライカワセミ属",
              "name-cn": "笑翠鸟属",
              "type": "genus",
              "icon-children": [
                {
                  "name": "dacelo novaeguineae",
                  "name-jp": "ワライカワセミ",
                  "name-cn": "笑翠鸟",
                  "type": "species",
                  "icon": "/icon/ワライカワセミ.jpg",
                  "hasWild": false
                }
              ]
            }
          ]
        }
      ]
    }
  ]
}